poke-base/__init__.py
poke-base/pokemon.csv
poke-base/random_pokemon.py
pokealan/__init__.py
pokealan/pokemon.csv
pokealan/random_pokemon.py
Pokealanbs-1.0.0.dist-info/METADATA
Pokealanbs-1.0.0.dist-info/WHEEL
Pokealanbs-1.0.0.dist-info/top_level.txt
Pokealanbs-1.0.0.dist-info/RECORD
